README.txt
setup.py
dbviewer.egg-info/PKG-INFO
dbviewer.egg-info/SOURCES.txt
dbviewer.egg-info/dependency_links.txt
dbviewer.egg-info/entry_points.txt
dbviewer.egg-info/requires.txt
dbviewer.egg-info/top_level.txt
src/__init__.py
src/addin_value.py
src/auxiliaries.py
src/config.py
src/controlpanel.py
src/copypaste.py
src/dbConnector.py
src/delete_data.py
src/mainloader.py
src/masterpanel.py
src/newfile.py
src/onevalue.py
src/remodelcol.py
src/savedialog.py
src/search_eng.py
src/tablegrid.py
src/tablemaker.py
src/update.py