Metadata-Version: 1.1
Name: dbviewer
Version: 0.2.1.0
Summary:  SQLite database editor/viewer
Home-page:  https://github.com/seabass808
Author: seabass808
Author-email: jyathux23@yahoo.co.jp
License: BSD
Platform: UNKNOWN
Classifier: Programming Language :: Python
Classifier: Programming Language :: Python :: 2
Classifier: Programming Language :: Python :: 2.7
Classifier: Topic :: Database
Classifier: License :: OSI Approved :: BSD License
Classifier: Operating System :: Unix
Classifier: Operating System :: POSIX
